casetagger/__init__.py
casetagger/cli.py
casetagger/config.py
casetagger/db.py
casetagger/debug.py
casetagger/logger.py
casetagger/models.py
casetagger/tagger.py
casetagger/util.py
casetagger-0.4.3.dist-info/DESCRIPTION.rst
casetagger-0.4.3.dist-info/METADATA
casetagger-0.4.3.dist-info/RECORD
casetagger-0.4.3.dist-info/WHEEL
casetagger-0.4.3.dist-info/entry_points.txt
casetagger-0.4.3.dist-info/metadata.json
casetagger-0.4.3.dist-info/top_level.txt
