Metadata-Version: 2.0
Name: casetagger
Version: 0.4.3
Summary: Part-of-speech and morphological tagger employing a simple cased-based algorithm.
Home-page: https://github.com/Typecraft/casetagger
Author: Tormod Haugland
Author-email: tormod.haugland@gmail.com
License: MIT license
Keywords: casetagger
Platform: UNKNOWN
Classifier: Development Status :: 2 - Pre-Alpha
Classifier: Intended Audience :: Developers
Classifier: License :: OSI Approved :: MIT License
Classifier: Natural Language :: English
Classifier: Programming Language :: Python :: 2
Classifier: Programming Language :: Python :: 2.6
Classifier: Programming Language :: Python :: 2.7
Classifier: Programming Language :: Python :: 3
Classifier: Programming Language :: Python :: 3.3
Classifier: Programming Language :: Python :: 3.4
Classifier: Programming Language :: Python :: 3.5
Requires-Dist: Click (>=6.0)
Requires-Dist: typecraft-python (>=0.3.1)
